mycodoc/__init__.py
mycodoc-0.1.0.dist-info/licenses/LICENSE
mycodoc-0.1.0.dist-info/METADATA
mycodoc-0.1.0.dist-info/WHEEL
mycodoc-0.1.0.dist-info/top_level.txt
mycodoc-0.1.0.dist-info/RECORD
